odoo/addons/base_external_dbsource_mysql/README.rst
odoo/addons/base_external_dbsource_mysql/__init__.py
odoo/addons/base_external_dbsource_mysql/__manifest__.py
odoo/addons/base_external_dbsource_mysql/demo/base_external_dbsource.xml
odoo/addons/base_external_dbsource_mysql/i18n/base_external_dbsource_mysql.pot
odoo/addons/base_external_dbsource_mysql/i18n/de.po
odoo/addons/base_external_dbsource_mysql/i18n/es.po
odoo/addons/base_external_dbsource_mysql/i18n/hr.po
odoo/addons/base_external_dbsource_mysql/i18n/it.po
odoo/addons/base_external_dbsource_mysql/i18n/nl_NL.po
odoo/addons/base_external_dbsource_mysql/i18n/pt_BR.po
odoo/addons/base_external_dbsource_mysql/i18n/sl.po
odoo/addons/base_external_dbsource_mysql/i18n/tr.po
odoo/addons/base_external_dbsource_mysql/models/__init__.py
odoo/addons/base_external_dbsource_mysql/models/base_external_dbsource.py
odoo/addons/base_external_dbsource_mysql/readme/CONFIGURE.md
odoo/addons/base_external_dbsource_mysql/readme/CONTRIBUTORS.md
odoo/addons/base_external_dbsource_mysql/readme/DESCRIPTION.md
odoo/addons/base_external_dbsource_mysql/readme/INSTALL.md
odoo/addons/base_external_dbsource_mysql/readme/ROADMAP.md
odoo/addons/base_external_dbsource_mysql/readme/USAGE.md
odoo/addons/base_external_dbsource_mysql/static/description/icon.png
odoo/addons/base_external_dbsource_mysql/static/description/index.html
odoo/addons/base_external_dbsource_mysql/tests/__init__.py
odoo/addons/base_external_dbsource_mysql/tests/test_base_external_dbsource.py
odoo_addon_base_external_dbsource_mysql-18.0.1.0.0.2.dist-info/METADATA
odoo_addon_base_external_dbsource_mysql-18.0.1.0.0.2.dist-info/WHEEL
odoo_addon_base_external_dbsource_mysql-18.0.1.0.0.2.dist-info/top_level.txt
odoo_addon_base_external_dbsource_mysql-18.0.1.0.0.2.dist-info/RECORD
