Metadata-Version: 2.1
Name: odoo-addon-base_external_dbsource_mysql
Version: 18.0.1.0.0.2
Requires-Python: >=3.10
Requires-Dist: mysqlclient
Requires-Dist: odoo-addon-base_external_dbsource==18.0.*
Requires-Dist: odoo==18.0.*
Requires-Dist: sqlalchemy
Summary: External Database Source - MySQL
Home-page: https://github.com/OCA/server-backend
License: LGPL-3
Author: Daniel Reis, LasLabs, Odoo Community Association (OCA)
Author-email: support@odoo-community.org
Classifier: Programming Language :: Python
Classifier: Framework :: Odoo
Classifier: Framework :: Odoo :: 18.0
Classifier: License :: OSI Approved :: GNU Lesser General Public License v3 (LGPLv3)
